CHANGES.txt
LICENCE.txt
MANIFEST.in
README.rst
requirements.txt
setup.py
django_keyval/__init__.py
django_keyval/admin.py
django_keyval/models.py
django_keyval/settings.py
django_keyval/tests.py
django_keyval/urls.py
django_keyval/wsgi.py
django_keyval.egg-info/PKG-INFO
django_keyval.egg-info/SOURCES.txt
django_keyval.egg-info/dependency_links.txt
django_keyval.egg-info/requires.txt
django_keyval.egg-info/top_level.txt
django_keyval/management/__init__.py
django_keyval/management/commands/__init__.py
django_keyval/management/commands/keyval.py