Metadata-Version: 1.0
Name: django-keyval
Version: 0.1.2
Summary: Simple django key-value store
Home-page: http://github.com/EdwinvO/django_keyval
Author: Edwin van Opstal
Author-email: evo.se-technology.com
License: LICENSE.txt
Platform: UNKNOWN
